MANIFEST.in
setup.cfg
setup.py
bika/__init__.py
bika.health.egg-info/PKG-INFO
bika.health.egg-info/SOURCES.txt
bika.health.egg-info/dependency_links.txt
bika.health.egg-info/entry_points.txt
bika.health.egg-info/namespace_packages.txt
bika.health.egg-info/not-zip-safe
bika.health.egg-info/requires.txt
bika.health.egg-info/top_level.txt
bika/health/__init__.py
bika/health/catalog.py
bika/health/config.py
bika/health/configure.zcml
bika/health/interfaces.py
bika/health/overrides.zcml
bika/health/permissions.py
bika/health/permissions.zcml
bika/health/profiles.zcml
bika/health/setuphandlers.py
bika/health/testing.py
bika/health/adapters/__init__.py
bika/health/adapters/configure.zcml
bika/health/adapters/widgetvisibility.py
bika/health/ajax/__init__.py
bika/health/ajax/ajaxhandler.py
bika/health/ajax/bikasetup.py
bika/health/ajax/client.py
bika/health/ajax/configure.zcml
bika/health/browser/__init__.py
bika/health/browser/bika-frontpage.pt
bika/health/browser/bika-frontpage.py
bika/health/browser/configure.zcml
bika/health/browser/overrides.zcml
bika/health/browser/aetiologicagent/__init__.py
bika/health/browser/aetiologicagent/configure.zcml
bika/health/browser/aetiologicagent/getaetiologicagents.py
bika/health/browser/aetiologicagent/getaetiologicagentsubtypes.py
bika/health/browser/analysis/__init__.py
bika/health/browser/analysis/configure.zcml
bika/health/browser/analysis/resultoutofrange.py
bika/health/browser/analysisrequest/__init__.py
bika/health/browser/analysisrequest/add.py
bika/health/browser/analysisrequest/ajax.py
bika/health/browser/analysisrequest/configure.zcml
bika/health/browser/analysisrequest/emailpopup.pt
bika/health/browser/analysisrequest/emailpopup.py
bika/health/browser/analysisrequest/invoice.py
bika/health/browser/analysisrequest/manageresults.py
bika/health/browser/analysisrequest/overrides.zcml
bika/health/browser/analysisrequest/publish.py
bika/health/browser/analysisrequest/view.py
bika/health/browser/analysisrequest/workflow.py
bika/health/browser/analysisrequest/templates/analysisrequest_invoice.pt
bika/health/browser/analysisrequest/templates/analysisrequest_invoice_content.pt
bika/health/browser/analysisrequest/templates/analysisrequest_invoice_print.pt
