Metadata-Version: 1.1
Name: bika.health
Version: 3.1.8
Summary: Bika Health Open Source LIS
Home-page: http://github.com/bikalabs/bika.health
Author: Naralabs
Author-email: info@naralabs.com
License: AGPL
Keywords: lims,health,bika,opensource
Platform: UNKNOWN
Classifier: Framework :: Plone
Classifier: Programming Language :: Python
Classifier: Development Status :: 5 - Production/Stable
Classifier: Environment :: Web Environment
Classifier: Intended Audience :: Healthcare Industry
Classifier: Intended Audience :: Information Technology
Classifier: Intended Audience :: Science/Research
Classifier: License :: OSI Approved :: GNU Affero General Public License v3 or later (AGPLv3+)
